italian_ats_evaluator/SimplificationAnalyzer.py
italian_ats_evaluator/TextAnalyzer.py
italian_ats_evaluator/__init__.py
italian_ats_evaluator/analyzers/BasicAnalyzer.py
italian_ats_evaluator/analyzers/DiffAnalyzer.py
italian_ats_evaluator/analyzers/LexiconAnalyzer.py
italian_ats_evaluator/analyzers/PosAnalyzer.py
italian_ats_evaluator/analyzers/ReadabilityAnalyzer.py
italian_ats_evaluator/analyzers/SimilarityAnalyzer.py
italian_ats_evaluator/analyzers/VerbsAnalyzer.py
italian_ats_evaluator/analyzers/__init__.py
italian_ats_evaluator/models/BasicEvaluation.py
italian_ats_evaluator/models/DiffEvaluation.py
italian_ats_evaluator/models/LexiconEvaluation.py
italian_ats_evaluator/models/PosEvaluation.py
italian_ats_evaluator/models/ReadabilityEvaluation.py
italian_ats_evaluator/models/SimilarityEvaluation.py
italian_ats_evaluator/models/SimplificationEvaluation.py
italian_ats_evaluator/models/Span.py
italian_ats_evaluator/models/TextEvaluation.py
italian_ats_evaluator/models/VerbsEvaluation.py
italian_ats_evaluator/models/__init__.py
italian_ats_evaluator/resources/difficult_connectives.txt
italian_ats_evaluator/resources/juridical_expressions.txt
italian_ats_evaluator/resources/latinisms.txt
italian_ats_evaluator/resources/nvdb_AD.txt
italian_ats_evaluator/resources/nvdb_AU.txt
italian_ats_evaluator/resources/nvdb_FO.txt
italian_ats_evaluator/utils/__init__.py
italian_ats_evaluator/utils/nlp_utils.py
italian_ats_evaluator-3.0.3.dist-info/LICENSE
italian_ats_evaluator-3.0.3.dist-info/METADATA
italian_ats_evaluator-3.0.3.dist-info/WHEEL
italian_ats_evaluator-3.0.3.dist-info/top_level.txt
italian_ats_evaluator-3.0.3.dist-info/RECORD
