Metadata-Version: 2.1
Name: italian-ats-evaluator
Version: 3.0.3
Summary: Italian ATS Evaluator
Author-email: RedHitMark <russodivito.marco@gmail.com>
Maintainer-email: RedHitMark <russodivito.marco@gmail.com>
License: MIT License
Project-URL: Repository, https://github.com/VerbACxSS/italian-ats-evaluator
Project-URL: Issues, https://github.com/VerbACxSS/italian-ats-evaluator/issues
Keywords: ats,text,simplification,italian,nlp
Classifier: Topic :: Scientific/Engineering
Classifier: Topic :: Scientific/Engineering :: Information Analysis
Classifier: Topic :: Scientific/Engineering :: Artificial Intelligence
Classifier: Topic :: Text Processing
Classifier: Topic :: Text Processing :: Linguistic
Classifier: Development Status :: 5 - Production/Stable
Classifier: License :: OSI Approved :: MIT License
Classifier: Programming Language :: Python :: 3
Classifier: Programming Language :: Python :: 3.8
Classifier: Programming Language :: Python :: 3.9
Classifier: Programming Language :: Python :: 3.10
Classifier: Programming Language :: Python :: 3.11
Classifier: Programming Language :: Python :: 3.12
Classifier: Programming Language :: Python :: 3.13
Classifier: Operating System :: OS Independent
Classifier: Intended Audience :: Developers
Classifier: Intended Audience :: Science/Research
Classifier: Intended Audience :: Education
Classifier: Natural Language :: Italian
Requires-Python: >=3.9
License-File: LICENSE
Requires-Dist: spacy <3.8.8,>=3.8.0
Requires-Dist: pyphen <0.18.0,>=0.17.0
Requires-Dist: editdistance <0.9.0,>=0.8.0
Requires-Dist: sentence-transformers <5.2.0,>=5.1.0
Provides-Extra: test
Requires-Dist: pytest ; extra == 'test'
